{
    "description": "项目配置文件。",
    "packOptions": {
        "ignore": []
    },
    "setting": {
        "urlCheck": false,
        "minified": true,
        "postcss": true,
        "es6": true
    },
    "compileType": "miniprogram",
    "libVersion": "",
    "appid": "wxdfec8f307cdae32c",
    "projectname": "车友汇-商家端",
    "simulatorType": "wechat",
    "simulatorPluginLibVersion": {},
    "condition": {
        "search": {
            "list": []
        },
        "conversation": {
            "list": []
        },
        "game": {
            "list": []
        },
        "miniprogram": {
            "list": []
        }
    }
}